event_hub_shared/__init__.py
event_hub_shared/consumer/event_consumer.py
event_hub_shared/deadletter/dead_letter_handler.py
event_hub_shared/emitter/event_emitter.py
event_hub_shared/handlers/base_handler.py
event_hub_shared/registry/event_registry.py
event_hub_shared/scheduler/service_bus_scheduler.py
event_hub_shared/types/events.py
event_hub_shared/types/handlers.py
event_hub_shared/utils/correlation.py
event_hub_shared/utils/filtering.py
event_hub_shared/utils/idempotency.py
event_hub_shared/utils/partitioning.py
flexwurx_event_hub_python-1.0.12.dist-info/METADATA
flexwurx_event_hub_python-1.0.12.dist-info/WHEEL
flexwurx_event_hub_python-1.0.12.dist-info/RECORD
