Metadata-Version: 2.4
Name: flexwurx-event-hub-python
Version: 1.0.12
Summary: Event Hub shared components for Python services
Author-email: FlexWurx <dev@flexwurx.com>
Classifier: Development Status :: 4 - Beta
Classifier: Intended Audience :: Developers
Classifier: Programming Language :: Python :: 3
Classifier: Programming Language :: Python :: 3.9
Classifier: Programming Language :: Python :: 3.10
Classifier: Programming Language :: Python :: 3.11
Classifier: Programming Language :: Python :: 3.12
Requires-Python: >=3.9
Requires-Dist: azure-eventhub-checkpointstoreblob>=1.2.0
Requires-Dist: azure-eventhub>=5.15.0
Requires-Dist: azure-identity>=1.19.0
Requires-Dist: azure-servicebus>=7.12.3
Requires-Dist: azure-storage-blob>=12.24.0
Requires-Dist: pydantic>=2.10.3
Provides-Extra: dev
Requires-Dist: black>=23.0.0; extra == 'dev'
Requires-Dist: mypy>=1.0.0; extra == 'dev'
Requires-Dist: pytest-asyncio>=0.21.0; extra == 'dev'
Requires-Dist: pytest>=7.0.0; extra == 'dev'
Requires-Dist: ruff>=0.1.0; extra == 'dev'
